setup.py
pktt/Binomialdistribution.py
pktt/Gaussiandistribution.py
pktt/Generaldistribution.py
pktt/__init__.py
pktt.egg-info/PKG-INFO
pktt.egg-info/SOURCES.txt
pktt.egg-info/dependency_links.txt
pktt.egg-info/not-zip-safe
pktt.egg-info/top_level.txt