Metadata-Version: 1.0
Name: pktt
Version: 1.2
Summary: Gaussian and Binomial distributions
Home-page: UNKNOWN
Author: Paul Tran
Author-email: tranpaul62@gmail.com
License: UNKNOWN
Platform: UNKNOWN
